awsswitch.py
awsswitch-0.2.2.dist-info/entry_points.txt
awsswitch-0.2.2.dist-info/LICENSE
awsswitch-0.2.2.dist-info/WHEEL
awsswitch-0.2.2.dist-info/METADATA
awsswitch-0.2.2.dist-info/RECORD
