Metadata-Version: 2.1
Name: awsswitch
Version: 0.2.2
Summary: AWS profile switcher
Author-email: Tobias Sauerwein <cgtobi@gmail.com>
Requires-Python: >=3.8
Classifier: License :: OSI Approved :: MIT License
Requires-Dist: inquirerpy >=0.3.3
Requires-Dist: pytest >=6.2.5 ; extra == "test"
Requires-Dist: pytest-cov ; extra == "test"
Project-URL: Home, https://github.com/cgtobi/awsswitch
Provides-Extra: test
